{
  "type": "service_account",
  "project_id": "facetest-b0450",
  "private_key_id": "e874de71a17269707450",
  "private_key": "-----BEGIN PRIVATE KEY-----\nMIIEvAIBADAOMSSa0Ip605y3g==\n-----END PRIVATE KEY-----\n",
  "client_email": "firebase-adminsviceaccount.com",
  "client_id": "1111936556706",
  "auth_uri": "https://accounts.go/oauth2/auth",
  "token_uri": "https://oauth2.googom/token",
  "auth_provider_x509_cert_url": "https://www.googleapis.com/oauth2/v1/certs",
  "client_x509_cert_url": "https://www.googleapis.com/robot/v1/metadata/x509/firebase-b0450.iam.gserviceaccount.com"
}
